fl_plugin_db_organiser/__init__.py
fl_plugin_db_organiser/__main__.py
fl_plugin_db_organiser/conftest.py
fl_plugin_db_organiser-1.1.0.dist-info/LICENSE
fl_plugin_db_organiser-1.1.0.dist-info/METADATA
fl_plugin_db_organiser-1.1.0.dist-info/WHEEL
fl_plugin_db_organiser-1.1.0.dist-info/entry_points.txt
fl_plugin_db_organiser-1.1.0.dist-info/top_level.txt
fl_plugin_db_organiser-1.1.0.dist-info/RECORD
