Metadata-Version: 2.1
Name: fl-plugin-db-organiser
Version: 1.1.0
Summary: Reads plugin database files (.nfo) created by FL Studio and reorganises them into folders based on plugin vendor names
Home-page: https://github.com/demberto/FL-PluginDB-Organiser
Author: demberto
Author-email: demberto@protonmail.com
License: MIT
Project-URL: Bug Tracker, https://github.com/demberto/FL-PluginDB-Organiser/issues
Project-URL: Changelog, https://github.com/demberto/FL-PluginDB-Organiser/blob/master/CHANGELOG.md
Classifier: Development Status :: 4 - Beta
Classifier: Environment :: Console
Classifier: Intended Audience :: End Users/Desktop
Classifier: License :: OSI Approved :: MIT License
Classifier: Natural Language :: English
Classifier: Operating System :: Microsoft :: Windows
Classifier: Operating System :: MacOS :: MacOS X
Classifier: Programming Language :: Python :: 3
Classifier: Programming Language :: Python :: 3 :: Only
Classifier: Programming Language :: Python :: 3.4
Classifier: Programming Language :: Python :: 3.5
Classifier: Programming Language :: Python :: 3.6
Classifier: Programming Language :: Python :: 3.7
Classifier: Programming Language :: Python :: 3.8
Classifier: Programming Language :: Python :: 3.9
Classifier: Programming Language :: Python :: 3.10
Classifier: Topic :: Utilities
Requires-Python: >=3.4
License-File: LICENSE
Requires-Dist: ansicolors
Requires-Dist: typing ; python_version < "3.5"
